listingcraft/__init__.py
listingcraft/cli.py
listingcraft/core/listing_generator.py
listingcraft/core/models.py
listingcraft/integrations/fastapi_integration.py
listingcraft/services/llm/openai_service.py
listingcraft/services/marketplaces/marketplace_service.py
listingcraft/services/vision/image_analyzer.py
listingcraft/utils/config.py
listingcraft-1.0.0.dist-info/licenses/LICENSE
listingcraft-1.0.0.dist-info/METADATA
listingcraft-1.0.0.dist-info/WHEEL
listingcraft-1.0.0.dist-info/entry_points.txt
listingcraft-1.0.0.dist-info/top_level.txt
listingcraft-1.0.0.dist-info/RECORD
