Metadata-Version: 2.4
Name: listingcraft
Version: 1.0.0
Summary: AI-powered product listing generation for marketplaces
Author-email: ListingCraft Team <hello@listingcraft.com>
License: MIT
Project-URL: Homepage, https://github.com/yourusername/listingcraft
Project-URL: Documentation, https://listingcraft.readthedocs.io
Project-URL: Repository, https://github.com/yourusername/listingcraft
Project-URL: Issues, https://github.com/yourusername/listingcraft/issues
Keywords: ai,marketplace,listing,ebay,poshmark,ecommerce,automation
Classifier: Development Status :: 4 - Beta
Classifier: Intended Audience :: Developers
Classifier: License :: OSI Approved :: MIT License
Classifier: Operating System :: OS Independent
Classifier: Programming Language :: Python :: 3
Classifier: Programming Language :: Python :: 3.8
Classifier: Programming Language :: Python :: 3.9
Classifier: Programming Language :: Python :: 3.10
Classifier: Programming Language :: Python :: 3.11
Classifier: Programming Language :: Python :: 3.12
Classifier: Topic :: Software Development :: Libraries :: Python Modules
Classifier: Topic :: Internet :: WWW/HTTP :: Dynamic Content
Classifier: Topic :: Scientific/Engineering :: Artificial Intelligence
Requires-Python: >=3.8
License-File: LICENSE
Requires-Dist: openai>=1.0.0
Requires-Dist: pydantic>=2.0.0
Requires-Dist: requests>=2.28.0
Provides-Extra: server
Requires-Dist: fastapi>=0.100.0; extra == "server"
Requires-Dist: uvicorn>=0.20.0; extra == "server"
Provides-Extra: dev
Requires-Dist: pytest>=7.0.0; extra == "dev"
Requires-Dist: black>=22.0.0; extra == "dev"
Requires-Dist: flake8>=5.0.0; extra == "dev"
Requires-Dist: mypy>=1.0.0; extra == "dev"
Provides-Extra: all
Requires-Dist: listingcraft[server]; extra == "all"
Dynamic: license-file
